{
  "wordSheet": [
    {
      "Word": "அ",
      "Letter": "அ",
      "Meaning": "தமிழ் எழுத்துகளுள் முதல் உயிர் எழுத்து ; சுட்டெழுத்து ; விகுதி ( அஃறிணைப் பன்மை , வியங்கோள் , எச்சம் ) ; ஆறாம் வேற்றுமைப்பன்மை உருபு ; சாரியை ; எட்டு என்னும் எண்ணின் குறி ; எதிர்மறை இடைச்சொல் ; அழகு ; கடவுள் ( சிவன் , திருமால் , பிரமன் ) ."
    },
    {
      "Word": "அஆ",
      "Letter": "அ-ஆ",
      "Meaning": "விட்டிசைச்சொல் ; வியப்புக் குறிப்பு ; இரக்கக் குறிப்பு ."
    },
    {
      "Word": "அஃகம்",
      "Letter": "அ-ஃ-க-ம்",
      "Meaning": "தானியம் ; விலைப்பொருள் ; ஊறுநீர் ; முறைமை ."
    },
    {
      "Word": "அஃகரம்",
      "Letter": "அ-ஃ-க-ர-ம்",
      "Meaning": "வெள்ளெருக்கு ."
    },
    {
      "Word": "அஃகல்",
      "Letter": "அ-ஃ-க-ல்",
      "Meaning": "காண்க : அஃகுதல் ."
    },
    {
      "Word": "அஃகாமை",
      "Letter": "அ-ஃ-கா-மை",
      "Meaning": "குறையாமை ; சுருங்காமை ."
    },
    {
      "Word": "அஃகான்",
      "Letter": "அ-ஃ-கா-ன்",
      "Meaning": "அ ' என்னும் முதல் எழுத்து ( அ - கான் , கான் எழுத்துச்சாரியை ) ."
    },
    {
      "Word": "அஃகு",
      "Letter": "அ-ஃ-கு",
      "Meaning": "ஊறுநீர் ."
    },
    {
      "Word": "அஃகுதல்",
      "Letter": "அ-ஃ-கு-த-ல்",
      "Meaning": "குறைதல் ; சுருங்குதல் ; நுணுகுதல் ; குவிதல் ; நெருங்குதல் ; வற்றுதல் ; கழிதல் ."
    },
    {
      "Word": "அஃகுல்லி",
      "Letter": "அ-ஃ-கு-ல்-லி",
      "Meaning": "உக்காரி என்னும் சிற்றுண்டி ; பிட்டு ."
    },
    {
      "Word": "அஃகுள்",
      "Letter": "அ-ஃ-கு-ள்",
      "Meaning": "காண்க : அக்குள் ."
    },
    {
      "Word": "அஃகேனம்",
      "Letter": "அ-ஃ-கே-ன-ம்",
      "Meaning": "ஆய்த எழுத்து , மூன்று புள்ளி ( ஃ ) வடிவினது , முள்ளில்லாப் பன்றி ."
    },
    {
      "Word": "அஃதான்று",
      "Letter": "அ-ஃ-தா-ன்-று",
      "Meaning": "( அஃது - அன்று ) அதுவுமன்றி ."
    },
    {
      "Word": "அஃது",
      "Letter": "அ-ஃ-து",
      "Meaning": "அஃறிணை ஒருமைச்சுட்டு ; அது ; அப்படி ."
    },
    {
      "Word": "அஃதை",
      "Letter": "அ-ஃ-தை",
      "Meaning": "அகதி , கதியிலி , திக்கற்றவர் , ஆதரவில்லாதவர் ."
    },
    {
      "Word": "அஃபோதம்",
      "Letter": "அ-ஃ-போ-த-ம்",
      "Meaning": "நிலாமுகிப்புள் , சகோரம் ; புறா ."
    },
    {
      "Word": "அஃறிணை",
      "Letter": "அ-ஃ-றி-ணை",
      "Meaning": "( அல் - திணை ) உயர்திணையல்லாதவை ; பகுத்தறிவற்ற உயிர்களும் உயிரற்றனவும் ; மக்கள் , தேவர் , நரகர் அல்லாத மற்றப் பொருள்கள் ."
    },
    {
      "Word": "அகக்கண்",
      "Letter": "அ-க-க்-க-ண்",
      "Meaning": "உள்ளறிவு ; ஞானம் ."
    },
    {
      "Word": "அகக்கரணம்",
      "Letter": "அ-க-க்-க-ர-ண-ம்",
      "Meaning": "உள்ளம் , மனம் ."
    },
    {
      "Word": "அகக்களி",
      "Letter": "அ-க-க்-க-ளி",
      "Meaning": "மனமகிழ்ச்சி ."
    },
    {
      "Word": "அகக்காழ்",
      "Letter": "அ-க-க்-கா-ழ்",
      "Meaning": "மரத்தின் உள்வயிரம் ; ஆண்மரம் ."
    },
    {
      "Word": "அகக்கூத்து",
      "Letter": "அ-க-க்-கூ-த்-து",
      "Meaning": "முக்குணம் சார்ந்த நடிப்பு ."
    },
    {
      "Word": "அகங்கரித்தல்",
      "Letter": "அ-க-ங்-க-ரி-த்-த-ல்",
      "Meaning": "செருக்குக்கொள்ளுதல் ."
    },
    {
      "Word": "அகங்கரிப்பு",
      "Letter": "அ-க-ங்-க-ரி-ப்-பு",
      "Meaning": "செருக்கு , அகங்காரம் ."
    },
    {
      "Word": "அகங்காரம்",
      "Letter": "அ-க-ங்-கா-ர-ம்",
      "Meaning": " நான் ' என்னும் செருக்கு , ஆணவம் ; உட்கரணம் நான்கனுள் ஒன்று ."
    },
    {
      "Word": "அகங்காரி",
      "Letter": "அ-க-ங்-கா-ரி",
      "Meaning": "செருக்குள்ளவன் ( ள்) ."
    },
    {
      "Word": "அகங்காழ்",
      "Letter": "அ-க-ங்-கா-ழ்",
      "Meaning": "காண்க : அகக்காழ் ."
    },
    {
      "Word": "அகங்கை",
      "Letter": "அ-க-ங்-கை",
      "Meaning": "( அகம் - கை ) உள்ளங்கை ."
    },
    {
      "Word": "அகசன்",
      "Letter": "அ-க-ச-ன்",
      "Meaning": "கேது என்னும் கோள் ."
    },
    {
      "Word": "அகசியம்",
      "Letter": "அ-க-சி-ய-ம்",
      "Meaning": "ஏளனச்சிரிப்பு ; வேடிக்கை ; பகடி ."
    },
    {
      "Word": "அகசு",
      "Letter": "அ-க-சு",
      "Meaning": "பொழுது ; பகல் ; இராப்பகல் கொண்டநாள் ."
    },
    {
      "Word": "அகசை",
      "Letter": "அ-க-சை",
      "Meaning": "மலையில் பிறந்தவள் , பார்வதி ."
    },
    {
      "Word": "அகச்சமயம்",
      "Letter": "அ-க-ச்-ச-ம-யம்",
      "Meaning": "சைவசமயத்தின் உட்பிரிவுகள் ; அவை : பாடாணவாத சைவம் , பேதவாத சைவம் , சிவசமவாத சைவம் , சிவசங்கிராந்தவாத சைவம் , ஈசுர அவிகாரவாத சைவம் , சிவாத்துவித சைவம் ."
    },
    {
      "Word": "அகச்சுட்டு",
      "Letter": "அ-க-ச்-சு-ட்-டு",
      "Meaning": "சொல்லின் முதனிலையாய்ப் பிரிவின்றி இணைந்து நிற்கும் சுட்டு ."
    },
    {
      "Word": "அகச்சுவை",
      "Letter": "அ-க-ச்-சு-வை",
      "Meaning": "அகப்பொருள் நெறிக்குரிய சுவை ; சத்துவம் முதலிய முக்குணம் வெளிப்பட நடிக்கும் நடிப்பு ."
    },
    {
      "Word": "அகடச்சக்கரம்",
      "Letter": "அ-க-ட-ச்-ச-க்-க-ர-ம்",
      "Meaning": "வயிற்றைச் சுற்றிக் கட்டும் உதரபந்தனம் என்னும் அணி , இடுப்பணி , அரைப்பட்டிகை ; கொடுங்கோல் மன்னன் ."
    },
    {
      "Word": "அகடம்",
      "Letter": "அ-க-ட-ம்",
      "Meaning": "பொல்லாங்கு ; அநீதி ; கபடம் ."
    },
    {
      "Word": "அகடவிகடம்",
      "Letter": "அ-க-ட-வி-க-ட-ம்",
      "Meaning": "சிரிக்கவைக்கும் பேச்சு ; வேடிக்கை ; தட்டுமாற்று ; இரண்டகம் ; வஞ்சகம் ; தந்திரம் ."
    },
    {
      "Word": "அகடிதகடனாசாமர்த்தியம்",
      "Letter": "அ-க-டி-த-க-ட-னா-சா-ம-ர்-த்-தி-ய-ம்",
      "Meaning": "செய்யக்கூடாதனவற்றைச் செய்விக்கும் வன்மை ."
    },
    {
      "Word": "அகடிதம்",
      "Letter": "அ-க-டி-த-ம்",
      "Meaning": "நிறைவேற்றற்கரியது ."
    },
    {
      "Word": "அகடியம்",
      "Letter": "அ-க-டி-ய-ம்",
      "Meaning": "பொல்லாங்கு ; அநீதி ; கபடம் ."
    },
    {
      "Word": "அகடு",
      "Letter": "அ-க-டு",
      "Meaning": "உள் ; வயிறு ; நடு ; மேடு ; நடுவுநிலை ; பொல்லாங்கு ."
    },
    {
      "Word": "அகடூரி",
      "Letter": "அ-க-டூ-ரி",
      "Meaning": "வயிற்றால் ஊர்ந்து செல்வது , பாம்பு ."
    },
    {
      "Word": "அகணி",
      "Letter": "அ-க-ணி",
      "Meaning": "உள் ; உட்பட்டது ; நம்பத்தக்க நட்பினர் ; தெங்கு , பனை முதலியவற்றின் மட்டைகளின் அகவாயிலிருந்து உரிக்கும் நார் ; வயல் ; மருதநிலம் ."
    },
    {
      "Word": "அகணிப்பாய்",
      "Letter": "அ-க-ணி-ப்-பா-ய்",
      "Meaning": "மூங்கிலாலான பாய் ."
    },
    {
      "Word": "அகண்",
      "Letter": "அ-க-ண்",
      "Meaning": "அண்மை , பக்கம் ."
    },
    {
      "Word": "அகண்டதீபம்",
      "Letter": "அ-க-ண்-ட-தீ-ப-ம்",
      "Meaning": "எப்பொழுதும் எரியும் விளக்கு , நந்தாவிளக்கு ."
    },
    {
      "Word": "அகண்டபரிபூரணம்",
      "Letter": "அ-க-ண்-ட-ப-ரி-பூ-ர-ண-ம்",
      "Meaning": "எங்கும் நிறைந்திருக்கை ; வேறுபாடின்றி எங்கும் நிறைந்திருக்கும் பரம் பொருள் ."
    },
    {
      "Word": "அகண்டம்",
      "Letter": "அ-க-ண்-ட-ம்",
      "Meaning": "துண்டிக்கப்படாதது ; பிளவுபடாதது ; முழுமை , முழுப் பொருள் ; பெரிய அகல்விளக்கு ; கடவுள் ."
    },
    {
      "Word": "அகண்டாகண்டன்",
      "Letter": "அ-க-ண்-டா-க-ண்-ட-ன்",
      "Meaning": "பரம்பொருள் ; எதற்கும் அஞ்சாதவன் ."
    },
    {
      "Word": "அகண்டாகாரஞானம்",
      "Letter": "அ-க-ண்-டா-கா-ர-ஞா-ன-ம்",
      "Meaning": "முற்றறிவு ."
    },
    {
      "Word": "அகண்டாகாரம்",
      "Letter": "அ-க-ண்-டா-கா-ர-ம்",
      "Meaning": "அளவுபடாத வடிவம் , பெருவடிவம் ; பெருவெளி ."
    },
    {
      "Word": "அகண்டி",
      "Letter": "அ-க-ண்-டி",
      "Meaning": "ஓர் இசைக்கருவி ."
    },
    {
      "Word": "அகண்டிதம்",
      "Letter": "அ-க-ண்-டி-த-ம்",
      "Meaning": "துண்டிக்கப்படாதது ; பிளவுபடாதது ; முழுமை , முழுப் பொருள் ; பெரிய அகல்விளக்கு ; கடவுள் ."
    },
    {
      "Word": "அகண்டிதன்",
      "Letter": "அ-க-ண்-டி-த-ன்",
      "Meaning": "பிளவுபடா இயல்பினன் ; முழுமையன் , கடவுள் ."
    },
    {
      "Word": "அகதகாரன்",
      "Letter": "அ-க-த-கா-ர-ன்",
      "Meaning": "மருத்துவன் ."
    },
    {
      "Word": "அகதம்",
      "Letter": "அ-க-த-ம்",
      "Meaning": "அழிவற்றது ; குளிகை ; மருந்து ; இன்பம் ."
    },
    {
      "Word": "அகதன்",
      "Letter": "அ-க-த-ன்",
      "Meaning": "நோயிலி ."
    },
    {
      "Word": "அகதி",
      "Letter": "அ-க-தி",
      "Meaning": "போக்கற்றவன் , கதியிலி ; வறியவன் ; தில்லைமரம் ; வேலமரம் ."
    },
    {
      "Word": "அகதேசி",
      "Letter": "அ-க-தே-சி",
      "Meaning": "உளளூரிலுள்ளவன் ; உள்நாட்டுப் பிச்சைவாங்கி ."
    },
    {
      "Word": "அகத்தடிமை",
      "Letter": "அ-க-த்-த-டி-மை",
      "Meaning": "இறைவன் அருகிலிருந்து செய்யும் அணுக்கத் தொண்டு ; வீட்டுப் பணியாளர் ."
    },
    {
      "Word": "அகத்தடியாள்",
      "Letter": "அ-க-த்-த-டி-யா-ள்",
      "Meaning": "வீட்டு வேலைக்காரி ."
    },
    {
      "Word": "அகத்தமிழ்",
      "Letter": "அ-க-த்-த-மி-ழ்",
      "Meaning": "அகத்திணைபற்றிய இலக்கியம் ."
    },
    {
      "Word": "அகத்தாழம்",
      "Letter": "அ-க-த்-தா-ழ-ம்",
      "Meaning": "மாலைப்பொழுது ."
    },
    {
      "Word": "அகத்தான்",
      "Letter": "அ-க-த்-தா-ன்",
      "Meaning": "உள்ளிடத்தில் இருப்பவன் ; மனத்தில் தங்கி இருப்பவன் ; இல்வாழ்வான் ; உறவினன் ; முற்றுகைக்குட்பட்டவன் ; மதில்காத்து உள்ளிருப்பவன் ."
    },
    {
      "Word": "அகத்திடுதல்",
      "Letter": "அ-க-த்-தி-டு-த-ல்",
      "Meaning": "செருகுதல் ; உள்ளிடுதல் ; கையால் உள்ளணைத்தல் ."
    },
    {
      "Word": "அகத்திணை",
      "Letter": "அ-க-த்-தி-ணை",
      "Meaning": "அகவொழுக்கம் , உள்ளொழுக்கம் ; கணவன் மனைவியரிடையே உள்ளத்தே நிகழும் இன்பவொழுக்கம் ; குறிஞ்சி , முல்லை , மருதம் , நெய்தல் , பாலை எனப்படும் ஐந்திணை ஒழுக்கம் ."
    },
    {
      "Word": "அகத்திணைப்புறம்",
      "Letter": "அ-க-த்-தி-ணை-ப்-பு-ற-ம்",
      "Meaning": "இன்ப வாழ்க்கைக்கு மாறுபட்டது ; கைக்கிளை பெருந்திணை ஒழுக்கங்கள் ."
    },
    {
      "Word": "அகத்தியம்",
      "Letter": "அ-க-த்-தி-ய-ம்",
      "Meaning": "கட்டாயம் ; அகத்தியர் செய்த ஓர் இலக்கண நூல் ."
    },
    {
      "Word": "அகத்தியல்",
      "Letter": "அ-க-த்-தி-ய-ல்",
      "Meaning": "உள்ளத்து இயற்கை , மனப்பாங்கு ."
    },
    {
      "Word": "அகத்திருத்துவம்",
      "Letter": "அ-க-த்-தி-ரு-த்-து-வ-ம்",
      "Meaning": "செயலின்றி நிற்கும் கடவுள் தன்மை ."
    },
    {
      "Word": "அகத்தீடு",
      "Letter": "அ-க-த்-தீ-டு",
      "Meaning": "உளளீடு ; எண்ணம் ; அன்பு ; கையால் உள்ளணைக்கை ; உள்ளடக்குதல் ."
    },
    {
      "Word": "அகத்துரைப்போன்",
      "Letter": "அ-க-த்-து-ரை-ப்-போ-ன்",
      "Meaning": "கடவுள் ; மனச்சாட்சி ."
    },
    {
      "Word": "அகத்துவங்கொள்ளுதல்",
      "Letter": "அ-க-த்-து-வ-ங்-கொ-ள்-ளு-த-ல்",
      "Meaning": "அடிப்படைக்காகத் தோண்டுதல் ."
    },
    {
      "Word": "அகத்துழிஞை",
      "Letter": "அ-க-த்-து-ழி-ஞை",
      "Meaning": "கோட்டையின் அகத்து உள்ளாரைப் புறத்தார் வெல்லும் புறத்துறை ."
    },
    {
      "Word": "அகத்தொண்டர்",
      "Letter": "அ-க-த்-தொ-ண்-ட-ர்",
      "Meaning": "வீட்டுப்பணிபுரிவோர் ."
    },
    {
      "Word": "அகத்தோர்",
      "Letter": "அ-க-த்-தோ-ர்",
      "Meaning": "உள்ளிருப்போர் ; ஊரார் ; ஒத்த உள்ளத்தராம் நண்பர் ."
    },
    {
      "Word": "அகநகர்",
      "Letter": "அ-க-ந-க-ர்",
      "Meaning": "கோட்டைக்குள் அடங்கிய நகரப்பகுதி ; அந்தப்புரம் ."
    },
    {
      "Word": "அகநகை",
      "Letter": "அ-க-ந-கை",
      "Meaning": "உட்சிரிப்பு ; இகழ்ச்சிச் சிரிப்பு ."
    },
    {
      "Word": "அகநாடக உரு",
      "Letter": "அ-க-நா-ட-க- உ-ரு",
      "Meaning": "அகக்கூத்திற்குரிய இசைப் பாட்டு வகை ; அவை : கந்தம் முதல் பிரபந்தம் ஈறாக இருபத்தெட்டு ."
    },
    {
      "Word": "அகநாடு",
      "Letter": "அ-க-நா-டு",
      "Meaning": "உள்நாடு ; மருதம் ."
    },
    {
      "Word": "அகநாழிகை",
      "Letter": "அ-க-நா-ழி-கை",
      "Meaning": "கருவறை ; உண்ணாழிகை ."
    },
    {
      "Word": "அகநிலை",
      "Letter": "அ-க-நி-லை",
      "Meaning": "உட்பட்டநிலை ; உள்ள நிலை ; உள்நகர் ; ஊர் ; நால்வகைத் தலைமைப் பண்களுள் ஒன்று ."
    },
    {
      "Word": "அகந்தை",
      "Letter": "அ-க-ந்-தை",
      "Meaning": "காண்க : அகங்காரம் ."
    },
    {
      "Word": "அகப்பகை",
      "Letter": "அ-க-ப்-ப-கை",
      "Meaning": "உட்பகை ."
    },
    {
      "Word": "அகப்படுதல்",
      "Letter": "அ-க-ப்-ப-டு-த-ல்",
      "Meaning": "உட்படுதல் ; பிடிக்கப்படுதல் ; சிக்கிக்கொள்ளுதல் ; கிட்டுதல் ."
    },
    {
      "Word": "அகப்படை",
      "Letter": "அ-க-ப்-ப-டை",
      "Meaning": "அணுக்கப்படை , மூலப்படை ."
    },
    {
      "Word": "அகப்பட்டி",
      "Letter": "அ-க-ப்-ப-ட்-டி",
      "Meaning": "சிறுதீங்கு செய்வோன் ; காவலின்றித் திரிவோன் ."
    },
    {
      "Word": "அகப்பணி",
      "Letter": "அ-க-ப்-ப-ணி",
      "Meaning": "மனச்சிந்தனை ; வீட்டுவேலை ."
    },
    {
      "Word": "அகப்பத்தியம்",
      "Letter": "அ-க-ப்-ப-த்-தி-ய-ம்",
      "Meaning": "மனவடக்கம் ; இணைவிழைச்சு இல்லாமை ."
    },
    {
      "Word": "அகப்பரம்",
      "Letter": "அ-க-ப்-ப-ர-ம்",
      "Meaning": "வீட்டைச் சார்ந்த மேடை ; திண்ணை , வேதிகை ."
    },
    {
      "Word": "அகப்பரிசாரம்",
      "Letter": "அ-க-ப்-ப-ரி-சா-ர-ம்",
      "Meaning": "வீட்டுவேலைக்காரர் ; அரண்மனைப் பணியாளர் ."
    },
    {
      "Word": "அகப்பரிவாரம்",
      "Letter": "அ-க-ப்-ப-ரி-வா-ர-ம்",
      "Meaning": "வீட்டுவேலைக்காரர் ; அரண்மனைப் பணியாளர் ."
    },
    {
      "Word": "அகப்பற்று",
      "Letter": "அ-க-ப்-ப-ற்-று",
      "Meaning": " நான் ' என்னும் உளப்பற்று மன விருப்பு ."
    },
    {
      "Word": "அகப்பா",
      "Letter": "அ-க-ப்-பா",
      "Meaning": "கோட்டை உள்மதில் ; மதிலுள் மேடை ; அகழி ; அகத்திணைப் பாட்டு ."
    },
    {
      "Word": "அகப்பாடு",
      "Letter": "அ-க-ப்-பா-டு",
      "Meaning": "உள்நிகழ்ச்சி ; நெருங்கியிருக்கை ."
    },
    {
      "Word": "அகப்பாட்டண்மையன்",
      "Letter": "அ-க-ப்-பா-ட்-ட-ண்-மை-ய-ன்",
      "Meaning": "மனமொத்த நண்பன் ; பிடிபடுந்தொலைவில் உள்ளவன் ."
    },
    {
      "Word": "அகப்பாட்டு",
      "Letter": "அ-க-ப்-பா-ட்-டு",
      "Meaning": "அகப்பொருள் பற்றிய பாட்டு ; அகநானூறு என்னும் நூல் ."
    },
    {
      "Word": "அகப்பாட்டுவண்ணம்",
      "Letter": "அ-க-ப்-பா-ட்-டு-வ-ண்-ண-ம்",
      "Meaning": "இறுதியடி முற்றுப் பெறாது இடையடி போன்று வரும் சந்தம் ."
    },
    {
      "Word": "அகப்பாட்டுறுப்பு",
      "Letter": "அ-க-ப்-பா-ட்-டு-று-ப்-பு",
      "Meaning": "அகப்பொருட் பாடல்களுக் குரிய பன்னிரண்டு உறுப்புகள் ; அவை : திணை , கைகோள் , கூற்று , கேட்போர் , இடம் , காலம் , பயன் , முன்னம் , மெய்ப்பாடு , எச்சம் , பொருள்வகை , துறை ."
    }
  ]
}